filter_local.py
filter_local_python.py
filter_test_support.py
filter_transform.py
filter_transform_python.py
dpk_filter_transform_python-0.2.0.dist-info/METADATA
dpk_filter_transform_python-0.2.0.dist-info/WHEEL
dpk_filter_transform_python-0.2.0.dist-info/top_level.txt
dpk_filter_transform_python-0.2.0.dist-info/RECORD
